PyLowCodeTest/Stack_data.py
PyLowCodeTest/Tools.py
PyLowCodeTest/__init__.py
PyLowCodeTest/main.py
PyLowCodeTest/modules_data.py
PyLowCodeTest/testing.py
WebTorchX-0.0.1.dist-info/LICENCE.txt
WebTorchX-0.0.1.dist-info/METADATA
WebTorchX-0.0.1.dist-info/WHEEL
WebTorchX-0.0.1.dist-info/entry_points.txt
WebTorchX-0.0.1.dist-info/top_level.txt
WebTorchX-0.0.1.dist-info/RECORD
