Metadata-Version: 2.1
Name: WebTorchX
Version: 0.0.1
Summary: LCTP is a Selenium-based Low-Code Web Testing Automation tool in Python. It simplifies web testing using JSON configuration files, making it easy for testers and developers to automate test scenarios. Also This module provides a command-line interface for various tasks related to the LCTP application. You can use this CLI to run tests, generate requirements files, format Python files, and perform extra functions.
Home-page: http://nagipragalathan.pythonanywhere.com/
Author: NagiPragalathan
Author-email: nagipragalathan@gmail.com
License: MIT
Classifier: Development Status :: 1 - Planning
Classifier: Intended Audience :: Developers
Classifier: Programming Language :: Python :: 3
Classifier: Operating System :: Unix
Classifier: Operating System :: MacOS :: MacOS X
Classifier: Operating System :: Microsoft :: Windows
License-File: LICENCE.txt
Requires-Dist: TerminalDesigner
Requires-Dist: webdriver-manager ==3.8.6
Requires-Dist: selenium ==4.9.0
Requires-Dist: black ==23.7.0
Requires-Dist: numpy ==1.23.5
Requires-Dist: Stack-data ==0.6.2
Requires-Dist: pyautogui ==0.9.53
Requires-Dist: pytest ==7.4.1
Requires-Dist: colorama
